music_artist/__init__.py
music_artist/__main__.py
music_artist/__version__.py
music_artist/artist.py
music_artist-1.0.2.dist-info/LICENSE
music_artist-1.0.2.dist-info/METADATA
music_artist-1.0.2.dist-info/WHEEL
music_artist-1.0.2.dist-info/top_level.txt
music_artist-1.0.2.dist-info/RECORD
